CTkExtendedGraph/CTkExtendedGraph.py
CTkExtendedGraph/__init__.py
CTkExtendedGraph-1.0.0.dist-info/LICENSE
CTkExtendedGraph-1.0.0.dist-info/METADATA
CTkExtendedGraph-1.0.0.dist-info/WHEEL
CTkExtendedGraph-1.0.0.dist-info/top_level.txt
CTkExtendedGraph-1.0.0.dist-info/RECORD
